fcwslib/__init__.py
fcwslib/server.py
fcwslib-3.0.0.dist-info/LICENSE
fcwslib-3.0.0.dist-info/METADATA
fcwslib-3.0.0.dist-info/WHEEL
fcwslib-3.0.0.dist-info/top_level.txt
fcwslib-3.0.0.dist-info/RECORD
